{
  "scope": "A",
  "description": "Temporary Ignition Identity Provider created during password reset which uses the User Source Profile named \"temp_0\".",
  "version": 1,
  "restricted": false,
  "overridable": true,
  "files": [
    "config.json"
  ],
  "attributes": {
    "lastModification": {
      "actor": "system-init",
      "timestamp": "2026-06-01T09:46:59Z"
    },
    "uuid": "29e9fb22-69fd-486e-91da-05e604c79129",
    "lastModificationSignature": "ded9fbc28a93dddebc0dae449f93bc88f37de84be1172fa0e6e0cd89bb4f99c4"
  }
}